thanos_cli/__init__.py
thanos_cli/__main__.py
thanos_cli/cli.py
thanos_cli/config.py
thanos_cli/protection.py
thanos_cli/snap.py
thanos_cli/utils.py
thanos_cli/weights.py
thanos_cli-0.3.0.dist-info/METADATA
thanos_cli-0.3.0.dist-info/WHEEL
thanos_cli-0.3.0.dist-info/entry_points.txt
thanos_cli-0.3.0.dist-info/licenses/LICENSE
thanos_cli-0.3.0.dist-info/RECORD
