Metadata-Version: 2.4
Name: thanos-cli
Version: 0.3.0
Summary: 🫰 Thanos - Eliminate half of all files with a snap. Perfectly balanced, as all things should be.
Project-URL: homepage, https://github.com/soldatov-ss/thanos
Project-URL: bugs, https://github.com/soldatov-ss/thanos/issues
Project-URL: changelog, https://github.com/soldatov-ss/thanos/blob/master/CHANGELOG.md
Project-URL: documentation, https://github.com/soldatov-ss/thanos/blob/master/docs/usage.md
Author-email: Soldatov Serhii <soldatov.own@gmail.com>
Maintainer-email: Soldatov Serhii <soldatov.own@gmail.com>
License: MIT
License-File: LICENSE
Keywords: cleanup,cli,files,thanos,utility
Classifier: Development Status :: 4 - Beta
Classifier: Intended Audience :: Developers
Classifier: Intended Audience :: System Administrators
Classifier: License :: OSI Approved :: MIT License
Classifier: Operating System :: OS Independent
Classifier: Programming Language :: Python :: 3
Classifier: Programming Language :: Python :: 3.9
Classifier: Programming Language :: Python :: 3.10
Classifier: Programming Language :: Python :: 3.11
Classifier: Programming Language :: Python :: 3.12
Classifier: Programming Language :: Python :: 3.13
Classifier: Topic :: System :: Filesystems
Classifier: Topic :: Utilities
Classifier: Typing :: Typed
Requires-Python: >=3.9
Requires-Dist: pathspec>=0.12.1
Requires-Dist: send2trash>=1.8.3
Requires-Dist: typer
Provides-Extra: test
Requires-Dist: coverage; extra == 'test'
Requires-Dist: ipdb; extra == 'test'
Requires-Dist: pre-commit>=4.3.0; extra == 'test'
Requires-Dist: pytest; extra == 'test'
Requires-Dist: ruff; extra == 'test'
Requires-Dist: ty; extra == 'test'
